README.rst
setup.cfg
setup.py
src/qante/__init__.py
src/qante/extracterror.py
src/qante/loc.py
src/qante/loclist.py
src/qante/loctuple.py
src/qante/loctuplelist.py
src/qante/query.py
src/qante/table.py
src/qante/tagger.py
src/qante/utilities.py
src/qante.egg-info/PKG-INFO
src/qante.egg-info/SOURCES.txt
src/qante.egg-info/dependency_links.txt
src/qante.egg-info/requires.txt
src/qante.egg-info/top_level.txt