Metadata-Version: 1.1
Name: qante
Version: 0.0.5
Summary: qante - Query ANnotated TExt
Home-page: https://github.com/AsgardSystems/qante.git
Author: Martha L. Escobar-Molano, David A. Barrett
Author-email: qante@asgard.com
License: BSD-3-Clause
Keywords: text,text processing,search,query,sequences,annotation
Platform: UNKNOWN
Classifier: Development Status :: 4 - Beta
Classifier: License :: OSI Approved :: BSD License
Classifier: Operating System :: OS Independent
Classifier: Programming Language :: Python :: 3
Classifier: Intended Audience :: Developers
Classifier: Topic :: Software Development :: Libraries :: Python Modules
Classifier: Topic :: Database
Classifier: Topic :: Internet :: WWW/HTTP :: Indexing/Search
Classifier: Topic :: Scientific/Engineering :: Information Analysis
Classifier: Topic :: Text Processing
Classifier: Topic :: Text Processing :: General
Classifier: Topic :: Text Processing :: Filters
Classifier: Topic :: Text Processing :: Indexing
